mobi/__init__.py
mobi/compatibility_utils.py
mobi/extract.py
mobi/kindleunpack.py
mobi/mobi_cover.py
mobi/mobi_dict.py
mobi/mobi_header.py
mobi/mobi_html.py
mobi/mobi_index.py
mobi/mobi_k8proc.py
mobi/mobi_k8resc.py
mobi/mobi_nav.py
mobi/mobi_ncx.py
mobi/mobi_opf.py
mobi/mobi_pagemap.py
mobi/mobi_sectioner.py
mobi/mobi_split.py
mobi/mobi_uncompress.py
mobi/mobi_utils.py
mobi/mobiml2xhtml.py
mobi/unipath.py
mobi/unpack_structure.py
mobi-0.4.0.dist-info/METADATA
mobi-0.4.0.dist-info/WHEEL
mobi-0.4.0.dist-info/entry_points.txt
mobi-0.4.0.dist-info/licenses/LICENSE
mobi-0.4.0.dist-info/RECORD
