Metadata-Version: 2.4
Name: mobi
Version: 0.4.0
Summary: unpack unencrypted mobi files
Project-URL: Homepage, https://github.com/iscc/mobi
Project-URL: Repository, https://github.com/iscc/mobi
Author-email: Titusz Pan <tp@py7.de>
License-Expression: GPL-3.0-only
License-File: LICENSE
Keywords: extract,mobi,mobipocket,text,unpack
Classifier: Development Status :: 4 - Beta
Requires-Python: >=3.9
Requires-Dist: loguru>=0.6
Requires-Dist: standard-imghdr>=3.13.0
